incline/__init__.py
incline/advanced.py
incline/gaussian_process.py
incline/multiscale.py
incline/seasonal.py
incline/statespace.py
incline/testing.py
incline/trend.py
incline-0.4.0.dist-info/WHEEL
incline-0.4.0.dist-info/METADATA
incline-0.4.0.dist-info/RECORD
