Metadata-Version: 2.3
Name: incline
Version: 0.4.0
Summary: Estimate Trend at a Particular Point in a Noisy Time Series
Keywords: time-series,derivative,slope,trend,savitzky-golay,spline
Author: Suriyan Laohaprapanon, Gaurav Sood
Author-email: Suriyan Laohaprapanon <suriyant@gmail.com>, Gaurav Sood <gsood07@gmail.com>
License: MIT
Classifier: Development Status :: 5 - Production/Stable
Classifier: Intended Audience :: Developers
Classifier: Intended Audience :: Science/Research
Classifier: Programming Language :: Python :: 3
Classifier: Programming Language :: Python :: 3.11
Classifier: Programming Language :: Python :: 3.12
Classifier: Programming Language :: Python :: 3.13
Classifier: Topic :: Scientific/Engineering :: Information Analysis
Classifier: Topic :: Software Development :: Libraries :: Python Modules
Classifier: Topic :: Utilities
Requires-Dist: pandas>=1.0.0
Requires-Dist: numpy>=1.18.0
Requires-Dist: scipy>=1.4.0
Requires-Dist: statsmodels>=0.13.0 ; extra == 'advanced'
Requires-Dist: scikit-learn>=1.0.0 ; extra == 'advanced'
Requires-Dist: matplotlib>=3.5.0 ; extra == 'advanced'
Requires-Dist: sphinx>=7.0 ; extra == 'docs'
Requires-Dist: furo>=2024.1.29 ; extra == 'docs'
Requires-Dist: myst-parser>=2.0 ; extra == 'docs'
Requires-Dist: linkify-it-py>=2.0 ; extra == 'docs'
Requires-Dist: jupyter-sphinx>=0.5.0 ; extra == 'docs'
Requires-Dist: ipykernel>=6.0.0 ; extra == 'docs'
Requires-Dist: matplotlib>=3.5.0 ; extra == 'docs'
Requires-Dist: sphinx-autoapi>=3.0 ; extra == 'docs'
Requires-Dist: sphinx-autodoc-typehints>=1.25 ; extra == 'docs'
Requires-Python: >=3.11
Project-URL: Documentation, https://finite-sample.github.io/incline/
Project-URL: Homepage, https://github.com/finite-sample/incline
Project-URL: Issues, https://github.com/finite-sample/incline/issues
Project-URL: Repository, https://github.com/finite-sample/incline
Provides-Extra: advanced
Provides-Extra: docs
